bintang/__init__.py
bintang/cell.py
bintang/column.py
bintang/core.py
bintang/iterdict.py
bintang/log.py
bintang/row.py
bintang/table.py
bintang/table_fcsv.py
bintang/table_fsql.py
bintang/table_mem.py
bintang/table_sqlbe.py
bintang-0.2.4.dist-info/LICENSE
bintang-0.2.4.dist-info/METADATA
bintang-0.2.4.dist-info/WHEEL
bintang-0.2.4.dist-info/top_level.txt
bintang-0.2.4.dist-info/RECORD
